{
  "id": "Q167541_cs_1",
  "metadata": {
    "DumpDate": "09/18/2024",
    "QID": "Q167541",
    "Date": "2026-02-24T00:27:35.070713",
    "ChunkID": 1,
    "Language": "cs"
  },
  "text": "Eredivisie, nejvyšší nizozemská fotbalová liga. Atributy zahrnuji: \n- stát: \"Nizozemsko\"\n- sport: \"fotbal\"\n- datum vytvoření / založení: \"1956\"\n- interval mezi událostmi: \"+1 rok\"\n- v původním jazyce: \"Eredivisie\"\n- začátek sezóny: \"srpen\"\n- kategorie na Commons: \"Eredivisie\"\n- počet účastníků: \"+18\"\n- počet zápasů či startů: \"+306\"\n- pořadatel: \"Královský nizozemský fotbalový svaz\"\n- podřazená liga: \"Eerste Divisie\"\n- počet odběratelů na sociálních sítích: \"+70452 (datum: 11 Uno 2023)\"\n- počet diváků/posluchačů: \"+467469 (datum: 5 Pro 2025)\""
}