{
  "id": "Q414_en_4",
  "metadata": {
    "Language": "en",
    "ChunkID": 4,
    "Date": "2026-02-26T00:36:23.188025",
    "QID": "Q414",
    "DumpDate": "09/18/2024"
  },
  "text": "Argentina, country in South America, also known as ARG, Argentine Republic, AR, Republic of Argentina, Republica Argentina. Attributes include: \n- driving side: \"right (start time: 10 Jun 1945)\",\n \"left (end time: 9 Jun 1945)\"\n- head of state: \"Javier Milei (start time: 10 Dec 2023 ; position held: President of Argentina ; replaces: Alberto Fernández)\"\n- on focus list of Wikimedia project: \"Wikipedia:List of articles all languages should have\",\n \"WikiProject African diaspora\"\n- lowest point: \"Laguna del Carbón (elevation above sea level: -105 metre)\"\n- official language: \"Spanish (nature of statement: de facto)\"\n- contains the administrative territorial entity: \"Buenos Aires Province\",\n \"Catamarca Province\",\n \"Chaco Province\",\n \"Córdoba Province\",\n \"Corrientes Province\",\n \"Entre Ríos Province\",\n \"Formosa Province\",\n \"Jujuy Province\",\n \"La Pampa\",\n \"La Rioja Province\",\n \"Mendoza Province\",\n \"Misiones Province\",\n \"Neuquén Province\",\n \"Río Negro Province\",\n \"Salta Province\",\n \"San Juan Province\",\n \"San Luis Province\",\n \"Santa Cruz Province\",\n \"Santa Fe Province\",\n \"Santiago del Estero Province\",\n \"Tierra del Fuego, Antarctica and South Atlantic Islands Province\",\n \"Tucumán Province\",\n \"Chubut Province\"\n- telephone country code: \"+54\"\n- significant event: \"Argentine economic crisis\"\n- flag: \"flag of Argentina\"\n- described by source: \"The Catholic Encyclopedia\",\n \"Brockhaus and Efron Encyclopedic Dictionary\",\n \"The Nuttall Encyclopædia (subject named as: Argentine Republic, Argentina)\",\n \"Encyclopædia Britannica 11th edition\",\n \"Pax Leksikon (volume: 1)\",\n \"Granat Encyclopedic Dictionary\"\n- main regulatory text: \"Constitution of Argentina\"\n- maintained by WikiProject: \"WikiProject Argentina\"\n- participant in: \"South American dreadnought race\",\n \"Global System of Trade Preferences among Developing Countries\",\n \"2018 G20 Buenos Aires summit\",\n \"Battle of Mount Longdon\",\n \"Falklands War\"\n- official name: \"República Argentina\"\n- language used: \"South Bolivian Quechua\",\n \"Yaghan\",\n \"Vilela\",\n \"Ona\",\n \"Iyojwa'ja Chorote\",\n \"Pilagá\",\n \"Joseph Mfonyam\",\n \"Abipón\",\n \"Wichí Lhamtés Nocten\",\n \"Toba Qom\",\n \"Mbyá Guaraní\",\n \"Mocoví\",\n \"Argentine Sign Language\",\n \"Santiagueño Quechua\",\n \"Spanish\",\n \"Wichí Lhamtés Vejoz\",\n \"Puelche\",\n \"Tehuelche\",\n \"Mapudungun\"\n- literacy rate: \"+99 percent (point in time: 2016)\"\n- suicide rate: \"+8.1 (point in time: 2019)\"\n- minimum temperature record: \"-32.8 degree Celsius (location: Sarmiento ; point in time: 1 Jun 1907)\"\n- GS1 country code: \"778-779\"\n- culture: \"culture of Argentina\"\n- VAT rate: \"+21 percent\"\n- motto text: \"Beats to your rhythm\",\n \"Curiad eich Rhythm\"\n- BTI Status Index: \"+7.21 (point in time: 2006)\",\n \"+7.34 (point in time: 2008)\",\n \"+7.25 (point in time: 2010)\",\n \"+6.95 (point in time: 2012)\",\n \"+6.76 (point in time: 2014)\",\n \"+6.65 (point in time: 2016)\",\n \"+7.27 (point in time: 2018)\",\n \"+7.29 (point in time: 2020)\",\n \"+6.73 (point in time: 2022)\"\n- BTI Governance Index: \"+5.46 (point in time: 2006)\",\n \"+5.91 (point in time: 2008)\",\n \"+5.56 (point in time: 2010)\",\n \"+5.28 (point in time: 2012)\",\n \"+5.01 (point in time: 2014)\",\n \"+4.78 (point in time: 2016)\",\n \"+6 (point in time: 2018)\",\n \"+6.1 (point in time: 2020)\",\n \"+5.52 (point in time: 2022)\"\n- economy of topic: \"economy of Argentina\"\n- replaces: \"Colonial Argentina\",\n \"United Provinces of the Río de la Plata\"\n- demographics of topic: \"demographics of Argentina\"\n- named after: \"silver\"\n- Democracy Index: \"+6.81 (point in time: 2021"
}