{
  "id": "Q84263196_fi_4",
  "metadata": {
    "QID": "Q84263196",
    "ChunkID": 4,
    "Date": "2026-03-02T13:37:05.320423",
    "Language": "fi",
    "DumpDate": "09/18/2024"
  },
  "text": "COVID-19, koronavirus SARS-CoV-2:n aiheuttama tartuntatauti, tunnetaan myös nimillä covid-19-tauti, koronavirustauti, covid-19, 2019-nCoV. Ominaisuuksia ovat: \n- riskitekijä: \"kohonnut verenpaine\",\n \"lihavuus\",\n \"diabetes\",\n \"sepelvaltimotauti\",\n \"immuunivaje\",\n \"keuhkoahtaumatauti\",\n \"autoimmuunisairaus\",\n \"hyperglykemia\",\n \"tupakointi\",\n \"astma\"\n- NCI-Thesaurus -tunniste: \"C171133\"\n- parantuneiden määrä: \"+88176 (ajankohta: 19 Maalis 2020)\",\n \"+123947 (ajankohta: 26 Maalis 2020)\",\n \"+212221 (ajankohta: 2 Huhti 2020)\",\n \"+356480 (ajankohta: 9 Huhti 2020)\",\n \"+548099 (ajankohta: 16 Huhti 2020)\",\n \"+756528 (ajankohta: 23 Huhti 2020)\",\n \"+1054822 (ajankohta: 30 Huhti 2020)\",\n \"+1365140 (ajankohta: 7 Touko 2020)\",\n \"+1721386 (ajankohta: 14 Touko 2020)\",\n \"+2109730 (ajankohta: 21 Touko 2020)\",\n \"+2623481 (ajankohta: 28 Touko 2020)\",\n \"+3286003 (ajankohta: 4 Kesä 2020)\",\n \"+3872520 (ajankohta: 11 Kesä 2020)\",\n \"+4546801 (ajankohta: 18 Kesä 2020)\",\n \"+5293269 (ajankohta: 25 Kesä 2020)\",\n \"+6162552 (ajankohta: 2 Heinä 2020)\",\n \"+7184897 (ajankohta: 9 Heinä 2020)\",\n \"+8279054 (ajankohta: 16 Heinä 2020)\",\n \"+9530110 (ajankohta: 23 Heinä 2020)\",\n \"+10930846 (ajankohta: 30 Heinä 2020)\",\n \"+12350509 (ajankohta: 6 Elo 2020)\",\n \"+14140697 (ajankohta: 14 Elo 2020)\",\n \"+19155936 (ajankohta: 5 Syys 2020)\",\n \"+17931490 (ajankohta: 31 Elo 2020)\",\n \"+15699085 (ajankohta: 21 Elo 2020)\",\n \"+43536986 (ajankohta: 29 Marras 2020)\",\n \"+33593848 (ajankohta: 31 Loka 2020)\",\n \"+50007028 (ajankohta: 10 Joulu 2020)\",\n \"+60282553 (ajankohta: 31 Joulu 2020)\",\n \"+67361614 (ajankohta: 15 Tammi 2021)\",\n \"+77230919 (ajankohta: 4 Helmi 2021)\",\n \"+90228716 (ajankohta: 28 Helmi 2021)\",\n \"+107802193 (ajankohta: 7 Huhti 2021)\",\n \"+137389609 (ajankohta: 9 Touko 2021)\",\n \"+168600129 (ajankohta: 3 Heinä 2021)\",\n \"+197142802 (ajankohta: 3 Syys 2021)\",\n \"+209460000 (ajankohta: 25 Syys 2021)\",\n \"+222522561 (ajankohta: 25 Loka 2021)\",\n \"+235353628 (ajankohta: 25 Marras 2021)\",\n \"+249880466 (ajankohta: 24 Joulu 2021)\",\n \"+278930965 (ajankohta: 22 Tammi 2022)\",\n \"+355954338 (ajankohta: 22 Helmi 2022)\",\n \"+379520916 (ajankohta: 7 Maalis 2022)\",\n \"+396411905 (ajankohta: 16 Maalis 2022)\",\n \"+408607739 (ajankohta: 21 Maalis 2022)\",\n \"+412802372 (ajankohta: 24 Maalis 2022)\",\n \"+420669396 (ajankohta: 29 Maalis 2022)\",\n \"+456516518 (ajankohta: 18 Huhti 2022)\",\n \"+460891054 (ajankohta: 22 Huhti 2022)\",\n \"+467602203 (ajankohta: 1 Touko 2022)\",\n \"+471603183 (ajankohta: 7 Touko 2022)\"\n- subjektilla on rooli: \"äkillinen hengitysvaikeusoireyhtymä\"\n- hoitamiseen käytettävä lääke: \"remdesiviiri\",\n \"kolkisiini\",\n \"fluvoksamiini (esityksen laatu: hypoteesi)\",\n \"infliksimabi\",\n \"aprepitantti\",\n \"ifenprodiili\",\n \"pratsosiini\"\n- sosiaalisen median seuraajat: \"+2282897 (ajankohta: 23 Touko 2023)\",\n \"+357740 (ajankohta: 23 Touko 2023)\""
}