{
  "id": "Q9617_de_1",
  "metadata": {
    "DumpDate": "09/18/2024",
    "QID": "Q9617",
    "Date": "2026-02-26T12:44:58.291422",
    "ChunkID": 1,
    "Language": "de"
  },
  "text": "FC Arsenal, Fußballverein aus London, England, Großbritannien, auch bekannt als Arsenal London, Arsenal Football Club, Arsenal FC, Arsenal F.C.. Attribute umfassen: \n- Liga oder Wettbewerb: „Premier League (Startzeitpunkt: 1919)“\n- Cheftrainer: „Mikel Arteta (Startzeitpunkt: 20 Dez 2019)“\n- Commons-Kategorie: „Arsenal F.C.“\n- Heimspielstätte: „Emirates Stadium (Startzeitpunkt: 22 Jul 2006)“\n- Sportart: „Fußball“\n- Teilnehmer an: „Premier League 2016/17“,\n „Premier League 2019/20“\n- ist ein(e): „Fußballverein“\n- Datum der Gründung, Entstehung, Erbauung: „1886“\n- offizieller Name: „Arsenal Football Club (Startzeitpunkt: 1919)“\n- Spitzname: „The Gunners (wörtliche Übersetzung: Els Canoners, Οι Κανονιέρηδες, Канониры, 枪手)“\n- Vorsitzender: „Stan Kroenke (Startzeitpunkt: Aug 2020)“\n- Hauptverwaltung: „London“\n- Staat: „Vereinigtes Königreich“\n- Inhaber von: „Manor Ground“,\n „Emirates Stadium“\n- offizielle Farbe: „Rot“,\n „Weiß“\n- Gründer: „David Danskin“\n- Sponsor: „Emirates“\n- verschieden von: „FC Arsenal“\n- Sieg: „Football League First Division 1988/89 (Zeitpunkt/Stand: 26 Mai 1989)“,\n „Premier League 2003/04 (Zeitpunkt/Stand: 25 Apr 2004)“\n- Sammlung mit Werk(en) dieser Person: „Nederlands Openluchtmuseum“\n- Anzahl der Follower: „+4620000 (Zeitpunkt/Stand: 25 Apr 2025)“\n- Name in Amts- oder Originalsprache: „Arsenal F.C.“\n- Name: „Arsenal“,\n „Arsenal“\n- Erster in einer Statistik: „Thierry Henry (erzielte Punkte/Tore: +228)“,\n „David O’Leary (Anzahl der gespielten Partien: +722)“"
}