{
  "id": "Q966898_en_1",
  "metadata": {
    "ChunkID": 1,
    "Date": "2026-02-26T01:38:39.983941",
    "Language": "en",
    "DumpDate": "09/18/2024",
    "QID": "Q966898"
  },
  "text": "Algemeen Nederlands Persbureau, business. Attributes include: \n- instance of: \"news agency\"\n- inception: \"1934\"\n- country: \"Netherlands\"\n- Commons category: \"Algemeen Nederlands Persbureau\"\n- industry: \"journalism\"\n- has works in the collection: \"National Museum of World Cultures\",\n \"NIOD Institute for War, Holocaust and Genocide Studies\",\n \"Dutch Resistance Museum\",\n \"Het Scheepvaartmuseum\"\n- social media followers: \"+1907 (point in time: 2 Jan 2021)\"\n- work location: \"Amsterdam\"\n- floruit: \"1949\"\n- field of work: \"journalism\",\n \"photography\"\n- product or material produced: \"news agency\"\n- archives at: \"Nationaal Archief (inventory number: 2.19.212)\""
}